<?xml version="1.0" encoding="UTF-8"?>
<mga>
	<MODELO comentario="Descriptivo del modelo." nombre="Creado por 'auto-destripador'." prefijo="fvr">
	<CAMPOS>
		<CAM nombre="sincro" descripcion="sincro" descripcionCorta="sincro" longitud="20" tipo="CHAR" />
		<CAM nombre="mark" descripcion="mark" descripcionCorta="mark" longitud="1" tipo="CHAR" />
		<CAM nombre="is_deleted" descripcion="is_deleted" descripcionCorta="is_deleted" longitud="1" tipo="CHAR" />
		<CAM nombre="author" descripcion="author" descripcionCorta="author" longitud="50" tipo="CHAR" />
		<CAM nombre="user_id" descripcion="user_id" descripcionCorta="user_id" longitud="50" tipo="CHAR" />
		<CAM nombre="role_id" descripcion="role_id" descripcionCorta="role_id" longitud="1" tipo="CHAR" />
		<CAM nombre="hash_code" descripcion="hash_code" descripcionCorta="hash_code" longitud="50" tipo="CHAR" />
		<CAM nombre="country_id" descripcion="country_id" descripcionCorta="country_id" longitud="5" tipo="NUM" />
		<CAM nombre="PS_name" descripcion="PS_name" descripcionCorta="PS_name" longitud="100" tipo="CHAR" />
		<CAM nombre="PS_flag_base64" descripcion="PS_flag_base64" descripcionCorta="PS_flag_base64" longitud="100" tipo="CHAR" />
		<CAM nombre="nick" descripcion="nick" descripcionCorta="nick" longitud="50" tipo="CHAR" />
		<CAM nombre="password" descripcion="password" descripcionCorta="password" longitud="50" tipo="CHAR" />
		<CAM nombre="first_name" descripcion="first_name" descripcionCorta="first_name" longitud="100" tipo="CHAR" />
		<CAM nombre="last_name" descripcion="last_name" descripcionCorta="last_name" longitud="100" tipo="CHAR" />
		<CAM nombre="phone" descripcion="phone" descripcionCorta="phone" longitud="100" tipo="CHAR" />
		<CAM nombre="gender" descripcion="gender" descripcionCorta="gender" longitud="1" tipo="CHAR" />
		<CAM nombre="birth_day" descripcion="birth_day" descripcionCorta="birth_day" longitud="10" tipo="CHAR" />
		<CAM nombre="avatar" descripcion="avatar" descripcionCorta="avatar" longitud="100" tipo="CHAR" />
		<CAM nombre="location_id" descripcion="location_id" descripcionCorta="location_id" longitud="50" tipo="CHAR" />
		<CAM nombre="json" descripcion="json" descripcionCorta="json" longitud="100" tipo="CHAR" />

	</CAMPOS>
	<ENTIDADES>
	<!-- US users -->
	<ENT nombre="users" descripcion="users" prefijo="us">
		<FMT archivo="T_US_users" nombre="Fisico" tipo="PHY">
			<CAM nombre="sincro" />
			<CAM nombre="mark" />
			<CAM nombre="is_deleted" />
			<CAM nombre="author" />
			<CAM nombre="user_id" />
			<CAM nombre="role_id" />
			<CAM nombre="hash_code" />
			<CAM nombre="country_id" />
			<CAM nombre="nick" />
			<CAM nombre="password" />
			<CAM nombre="first_name" />
			<CAM nombre="last_name" />
			<CAM nombre="phone" />
			<CAM nombre="gender" />
			<CAM nombre="birth_day" />
			<CAM nombre="avatar" />
			<CAM nombre="location_id" />
			<CAM nombre="json" />
		</FMT>
		<FMT archivo="T_US_users" nombre="Actualizacion" tipo="UPD">
			<CAM nombre="sincro" />
			<CAM nombre="mark" />
			<CAM nombre="is_deleted" />
			<CAM nombre="author" />
			<CAM nombre="user_id" />
			<CAM nombre="role_id" />
			<CAM nombre="hash_code" />
			<CAM nombre="country_id" />
			<CAM nombre="nick" />
			<CAM nombre="password" />
			<CAM nombre="first_name" />
			<CAM nombre="last_name" />
			<CAM nombre="phone" />
			<CAM nombre="gender" />
			<CAM nombre="birth_day" />
			<CAM nombre="avatar" />
			<CAM nombre="location_id" />
			<CAM nombre="json" />
			<KEY nombre="user_id" orden="ASC" secuencia="1" />
		</FMT>
		<FMT archivo="V_US_RTV_users" nombre="Recuperacion" tipo="RTV">
			<CAM nombre="sincro" />
			<CAM nombre="mark" />
			<CAM nombre="is_deleted" />
			<CAM nombre="author" />
			<CAM nombre="user_id" />
			<CAM nombre="role_id" />
			<CAM nombre="hash_code" />
			<CAM nombre="country_id" />
			<CAM nombre="PS_name" />
			<CAM nombre="PS_flag_base64" />
			<CAM nombre="nick" />
			<CAM nombre="password" />
			<CAM nombre="first_name" />
			<CAM nombre="last_name" />
			<CAM nombre="phone" />
			<CAM nombre="gender" />
			<CAM nombre="birth_day" />
			<CAM nombre="avatar" />
			<CAM nombre="location_id" />
			<CAM nombre="json" />
			<KEY nombre="user_id" orden="ASC" secuencia="1" />
		</FMT>
	</ENT>

	</ENTIDADES>

	</MODELO>
</mga>